pyami_asterisk/__init__.py
pyami_asterisk/client.py
pyami_asterisk/utils.py
pyami_asterisk-1.5.2.dist-info/LICENSE
pyami_asterisk-1.5.2.dist-info/METADATA
pyami_asterisk-1.5.2.dist-info/WHEEL
pyami_asterisk-1.5.2.dist-info/top_level.txt
pyami_asterisk-1.5.2.dist-info/RECORD
