Metadata-Version: 2.1
Name: pyami-asterisk
Version: 1.5.2
Summary: pyami_asterisk is a library based on python’s AsyncIO with Asterisk AMI
Home-page: https://github.com/streltsovdenis/pyami_asterisk.git
Author: Denis Streltsov
Author-email: sdv.streltsov@gmail.com
License: MIT license
Keywords: AMI,Asterisk,asyncio,python
Classifier: Development Status :: 4 - Beta
Classifier: Environment :: Console
Classifier: Intended Audience :: Developers
Classifier: License :: OSI Approved :: MIT License
Classifier: Operating System :: OS Independent
Classifier: Programming Language :: Python
Classifier: Programming Language :: Python :: 3.7
Classifier: Programming Language :: Python :: 3.8
Classifier: Programming Language :: Python :: 3.9
Classifier: Programming Language :: Python :: 3.10
Classifier: Topic :: Communications :: Telephony
Classifier: Topic :: Software Development :: Libraries :: Python Modules
License-File: LICENSE
Requires-Dist: loguru (==0.6.0)
